rule_engine_core/__init__.py
rule_engine_core/entity_base.py
rule_engine_core/entity_dao.py
rule_engine_core/entity_types.py
rule_engine_core/filter.py
rule_engine_core/metadata_store.py
rule_engine_core/parser.py
rule_engine_core/rule.py
rule_engine_core-0.0.2.dist-info/METADATA
rule_engine_core-0.0.2.dist-info/WHEEL
rule_engine_core-0.0.2.dist-info/top_level.txt
rule_engine_core-0.0.2.dist-info/RECORD
